cve_bin_tool/__init__.py
cve_bin_tool/async_utils.py
cve_bin_tool/cli.py
cve_bin_tool/config.py
cve_bin_tool/config_generator.py
cve_bin_tool/csv2cve.py
cve_bin_tool/cve_scanner.py
cve_bin_tool/cvedb.py
cve_bin_tool/egg_updater.py
cve_bin_tool/error_handler.py
cve_bin_tool/extractor.py
cve_bin_tool/fetch_json_db.py
cve_bin_tool/file.py
cve_bin_tool/format_checkers.py
cve_bin_tool/helper_script.py
cve_bin_tool/input_engine.py
cve_bin_tool/linkify.py
cve_bin_tool/log.py
cve_bin_tool/merge.py
cve_bin_tool/mismatch_loader.py
cve_bin_tool/nvd_api.py
cve_bin_tool/package_list_parser.py
cve_bin_tool/strings.py
cve_bin_tool/theme.py
cve_bin_tool/util.py
cve_bin_tool/validator.py
cve_bin_tool/version.py
cve_bin_tool/version_compare.py
cve_bin_tool/version_scanner.py
cve_bin_tool/version_signature.py
cve_bin_tool/available_fix/__init__.py
cve_bin_tool/available_fix/debian_cve_tracker.py
cve_bin_tool/available_fix/redhat_cve_tracker.py
cve_bin_tool/checkers/__init__.py
cve_bin_tool/checkers/accountsservice.py
cve_bin_tool/checkers/acpid.py
cve_bin_tool/checkers/apache_http_server.py
cve_bin_tool/checkers/apcupsd.py
cve_bin_tool/checkers/apparmor.py
cve_bin_tool/checkers/asn1c.py
cve_bin_tool/checkers/assimp.py
cve_bin_tool/checkers/asterisk.py
cve_bin_tool/checkers/atftp.py
cve_bin_tool/checkers/avahi.py
cve_bin_tool/checkers/axel.py
cve_bin_tool/checkers/bash.py
cve_bin_tool/checkers/bind.py
cve_bin_tool/checkers/binutils.py
cve_bin_tool/checkers/bird.py
cve_bin_tool/checkers/bison.py
cve_bin_tool/checkers/bluez.py
cve_bin_tool/checkers/boinc.py
cve_bin_tool/checkers/botan.py
cve_bin_tool/checkers/bro.py
cve_bin_tool/checkers/bubblewrap.py
cve_bin_tool/checkers/busybox.py
cve_bin_tool/checkers/bwm_ng.py
cve_bin_tool/checkers/bzip2.py
cve_bin_tool/checkers/c_ares.py
cve_bin_tool/checkers/capnproto.py
cve_bin_tool/checkers/ceph.py
cve_bin_tool/checkers/chess.py
cve_bin_tool/checkers/chrony.py
cve_bin_tool/checkers/civetweb.py
cve_bin_tool/checkers/clamav.py
cve_bin_tool-3.4.dist-info/LICENSE.md
cve_bin_tool-3.4.dist-info/METADATA
cve_bin_tool-3.4.dist-info/WHEEL
cve_bin_tool-3.4.dist-info/entry_points.txt
cve_bin_tool-3.4.dist-info/top_level.txt
cve_bin_tool-3.4.dist-info/RECORD
