Metadata-Version: 2.1
Name: cve-bin-tool
Version: 3.4
Summary: CVE Binary Checker Tool
Home-page: https://github.com/intel/cve-bin-tool
Author: Terri Oda
Author-email: terri.oda@intel.com
Maintainer: Terri Oda
Maintainer-email: terri.oda@intel.com
License: GPL-3.0-or-later
Keywords: security,tools,CVE
Classifier: Development Status :: 5 - Production/Stable
Classifier: Intended Audience :: Developers
Classifier: License :: OSI Approved :: GNU General Public License (GPL)
Classifier: Natural Language :: English
Classifier: Operating System :: OS Independent
Classifier: Programming Language :: Python :: 3.8
Classifier: Programming Language :: Python :: 3.9
Classifier: Programming Language :: Python :: 3.10
Classifier: Programming Language :: Python :: 3.11
Classifier: Programming Language :: Python :: Implementation :: CPython
Classifier: Programming Language :: Python :: Implementation :: PyPy
Requires-Python: >=3.8
License-File: LICENSE.md
Requires-Dist: aiohttp[speedups] >=3.9.4
Requires-Dist: beautifulsoup4
Requires-Dist: cvss
Requires-Dist: defusedxml
Requires-Dist: distro
Requires-Dist: filetype >=1.2.0
Requires-Dist: gsutil
Requires-Dist: jinja2 >=2.11.3
Requires-Dist: jsonschema >=3.0.2
Requires-Dist: lib4sbom >=0.7.2
Requires-Dist: lib4vex >=0.2.0
Requires-Dist: python-gnupg
Requires-Dist: packageurl-python
Requires-Dist: packaging >=22.0
Requires-Dist: plotly
Requires-Dist: pyyaml >=5.4
Requires-Dist: requests >=2.32.2
Requires-Dist: rich
Requires-Dist: rpmfile >=1.0.6
Requires-Dist: setuptools >=70.0.0
Requires-Dist: urllib3 >=2.2.2
Requires-Dist: xmlschema
Requires-Dist: zipp >=3.19.1
Requires-Dist: importlib-metadata >=3.6 ; python_version < "3.10"
Requires-Dist: toml ; python_version < "3.11"
Requires-Dist: importlib-resources ; python_version < "3.9"
Requires-Dist: zstandard ; python_version >= "3.4"
Provides-Extra: pdf
Requires-Dist: reportlab ; extra == 'pdf'
